LICENSE
multilingual/__init__.py
multilingual/main.py
multilingual-0.1.1.dist-info/entry_points.txt
multilingual-0.1.1.dist-info/LICENSE
multilingual-0.1.1.dist-info/WHEEL
multilingual-0.1.1.dist-info/METADATA
multilingual-0.1.1.dist-info/RECORD
