Metadata-Version: 2.1
Name: multilingual
Version: 0.1.1
Summary: A command line application that automatically translates the input sentence to multiple languages adds the translations to respective translation json files
Home-page: https://github.com/furkantanyol/multilingual
License: MIT
Keywords: translation,translations,automated translations
Author: Furkan Tanyol
Author-email: ftanyol@securecodewarrior.com
Requires-Python: >=3.10,<4.0
Classifier: License :: OSI Approved :: MIT License
Classifier: Programming Language :: Python :: 3
Classifier: Programming Language :: Python :: 3.10
Requires-Dist: googletrans (>=4.0.0rc1,<5.0.0)
Requires-Dist: typer (>=0.4.0,<0.5.0)
Project-URL: Repository, https://github.com/furkantanyol/multilingual
